{  
    "BREYNCIT": { 
        "name": "БРЕЙНЦИТ р-р оральный 100мг/мл  30 мл", 
        "tavsif": "Брейнцит – способствует улучшению когнитивных функций мозга!\n Раствор для питья 30 мл, с удобным шприцом-дозатором в комплекте \nБез сахара!   Без спирта!\nСостав:\nАктивные вещества в 1 мл раствора:\nЦитиколин…………………………………….100 мг\nЭкстракт шиповника……………………….2 мг",  
        "hajm": "В ориг.(уп.) 50шт",  
        "rasm_path": "img//breyncit.jpg"  
    },  
    "VIRAGEM": {
        "name": "ВИРАГЕМ сироп без сахара 100 мл",  
        "tavsif": "Вирагем - Поддерживает здоровый уровень гемоглобина в крови!\nСироп 100 мл\nБез сахара!   Без спирта! \nСостав:\nАктивные вещества в 5 мл сиропа:\nЖелезо (в виде бисглицината)………………..20 мг\nВитамин С (аскорбиновая кислота)……….60 мг\nВитамин В9 (фолиевая кислота)………….100 мкг\nВитамин В12 (цианокобаламин)…………..1,5 мкг \nЦинк (в виде цитрата)…………………………..3 мг",  
        "hajm": "В ориг.(уп.) 30шт",  
        "rasm_path": "img//viragem.jpg"  
    },  
    "IZOLIT": {
        "name": "ИЗОЛИТ с цинком р-р оральный 300 мл",
        "tavsif": "Изолит Цинк - экстренная помощь при обезвоживании!\nРегидратационный раствор 300 мл\nСостав:\nАктивные вещества в 300 мл раствора:\nДекстроза моногидрат .......... 3,90 г\nНатрия цитрат .......... 860 мг\nНатрия хлорид .......... 770 мг\nКалия хлорид .......... 440 мг\nЦинка цитрат .......... 6 мг",  
        "hajm": "В ориг.(уп.) 20шт",  
        "rasm_path": "img//izolit.jpg"
    },  
    "KALERON": {  
        "name": "КАЛЕРОН сироп без сахара 100 мл",
        "tavsif": "Калерон -  для укрепления костной ткани! \n Сироп 100 мл \n  Без сахара!   Без спирта! \n Состав: \n Активные вещества в 5 мл сиропа: \n Кальция цитрат .......... 200 мг \n Магния бисглицинат .......... 40 мг \n Цинка цитрат .......... 3 мг\n Витамин Д3(холекальциферол) .......... 2,5 мкг",
        "hajm": "В ориг.(уп.) 30шт",  
        "rasm_path": "img//kaleron.jpg"  
    },  
    "KARNIKID": {  
        "name": "КАРНИКИД сироп без сахара 50 мл",
        "tavsif": "\nКарникид - лёгкий способ поддержать здоровье и активность вашего ребенка!\nСироп 50 млБез сахара!   Без спирта!\nАктивные вещества в 5 мл сиропа:\nЛевокарнитин .......... 500 мг\nВитамин В6 (пиридоксина г/хл) .......... 1 мг\nВитамин С (аскорбиновая кислота) .......... 20 мг\nМагния бисглицинат .......... 20 мг",  
        "hajm": "В ориг.(уп.) 50шт",  
        "rasm_path": "img\\karnikid.jpg"  
    },  
    "RELAFLOR": {  
        "name": "РЕЛАФЛОР капли  8мл",
        "tavsif": "Релафлор - Спокойствие и комфорт вашего малыша, синбиотик в каплях для здорового животика!\nКапли 8 мл \nБез сахара!   Без спирта!\nВ 1 капле:\nBifidobacterium bifidum .......... 6.25*10 КОЕ\n\nBifidobacterium longum .......... 6.25*10 КОЕ\nLactobacillus acidophilus .......... 2.5*10 КОЕ\nВитамин Д3 (холекальциферол) .......... 400 МЕ",  
        "hajm": "В ориг.(уп.) 50 шт",  
        "rasm_path": "img//relaflor.jpg"  
    },  
    "SINIMAG": {  
        "name": "СИНИМАГ сироп  без сахара 100 мл",
        "tavsif": "Синимаг – способствует поддержанию спокойствия и улучшает работу нервной системы!\nСироп 100 мл\n Без сахара!   Без спирта! \n Состав:\n Активные вещества в 5 мл сиропа: \n Магний (в виде бисглицината) .......... 50 мг\n Витамин С (аскорбиновая кислота) .......... 10 мг \n Витамин В1 (тиамина гидрохлорид) .......... 1,2 мг \n Витамин В6 (пиридоксина гидрохлорид) .......... 1 мг\n (Витамин В12)( цианокобаламин) .......... 0,5 мкг",
        "hajm": "В ориг.(уп.) 30шт",  
        "rasm_path": "img//sinimag.jpg"  
    },  
    "SONAYT": {  
        "name": "СОНАЙТ капли  30 мл",
        "tavsif": "Сонайт – капелька спокойствия в каждом сне!\n Капли 30 мл\n Без сахара!   Без спирта!\n Состав: \n Активные вещества в 1 капле:\n Мелатонин .......... 60 мг\n Глицин .......... 60 мг",
        "hajm": "В ориг.(уп.) 50шт",  
        "rasm_path": "img//sonayt.jpg"  
    },  
    "ZINKID": {  
        "name": "ЗИНКИД сироп  без сахара  100 мл",
        "tavsif": "Зинкид – поддерживает и укрепляет иммунитет!\nСироп 100 мл\n Без сахара!   Без спирта!\nАктивные вещества в 5 мл сиропа:\nЦинка цитрат .......... 5 мг\nВитамин С (аскорбиновая кислота) .......... 50 мг",  
        "hajm": "В ориг.(уп.) 30шт",  
        "rasm_path": "img//zinkid.jpg"  
    },  
    "RESLIP": {  
        "name": "РЕСЛИП капли  20 мл",
        "tavsif": "Реслип – от вздутия животика! \n Капли 20 мл \n Без сахара!   Без спирта \n Состав:\n Активные вещества в 1 мл (20 капель): \n Симетикон .......... 66,5 мг \n Эфирное масло фенхеля .......... 1 мг \n",  
        "hajm": "В ориг.(уп.) 50шт",  
        "rasm_path": "img//reslip.jpg"  
    },  
    "ELVIKID": {  
        "name": "ЭЛВИКИД капля 30 мл (Б комплекс)",
        "tavsif": "Элвикид - для ясного ума, крепких нервов и сбалансированного развития!\nКапли 30 мл\nБез сахара!   Без спирта!\nСостав: \nАктивные вещества в 1 капле:\nВитамин В1 (тиамина гидрохлорид) .......... 1,2 мг\nВитамин В2 (рибофлавин) .......... 1,0 мг\nВитамин В3 (никотиновая кислота) .......... 14 мг\nВитамин В5 (пантотеновая кислота) .......... 4,0 мг\nВитамин В6 (пиридоксина гидрохлорид) .......... 1,2 мг\nВитамин В9 (фолиевая кислота) .......... 150мкг\nВитамин В12 (цианокобаламин) .......... 1,2 мкг",  
        "hajm": "В ориг.(уп.) 50шт",  
        "rasm_path": "img//elvikid.jpg"  
    },  
    "MAGNIY B": {  
        "name": "СУПРИМ МАГНИЙ В6 капс №30",
        "tavsif": "Суприм Магний В6 – асаб тизими, мушаклар ва юрак фаолиятини қўллаб-қувватловчи биологик фаол қўшимча.\n\nТаркиби (1 капсулада):\n• Магний (цитрат шаклида) – 150 мг\n• Витамин B6 (пиридоксина гидрохлорид) – 2 мг\n\nФойдаси:\n• Магний танқислигини бартараф этади\n• Асаб тизимини тинчлантиради\n• Мушак тиришишларини камайтиради\n\nҚўллаш тартиби: 1 капсуладан кунига 1–2 марта, овқат пайтида.\n\nҚўллашга қарши кўрсатма: аллергия, буйрак етишмовчилиги.\n\nҚандсиз. Глютенсиз. ГМОсиз.",  
        "hajm": "В ориг.(уп.) 50шт",  
        "rasm_path": "img//magniy_b6.jpg"  
    },  
    "KALTSIY+D3": {
        "name": "КАЛЦИЙ+Д3 таб №50 (со вкусом апельсин)",  
        "tavsif": "Кальций + D3 – суяклар ва тишлар мустаҳкамлиги учун муҳим минерал ва витамин мажмуаси.\n\nТаркиби (1 таблеткада):\n• Кальций карбонати – 500 мг (эквив. элементар кальций 200 мг)\n• Витамин D3 (холекальциферол) – 400 ХБ\n\nФойдаси:\n• Суяк ва тиш тўқималарини мустаҳкамлайди\n• Остеопороз хавфини камайтиради\n• Кальцийнинг ичакда сўрилишини яхшилайди\n\nҚўллаш тартиби: 1–2 таблеткадан кунига, овқат билан бирга чайнаб қабул қилиш тавсия этилади.\n\nҚўллашга қарши кўрсатма: гиперкальциемия, D витамини гипервитаминози, буйрак тошлари.\n\nАпельсин таъми. Қандсиз. Глютенсиз.",  
        "hajm": "В ориг.(уп.) 50шт",  
        "rasm_path": "img//kalsiy_d3.jpg"  
    },  
    "ARTROZIT": {  
        "name": "АРТРОЗИТ таб №30",
        "tavsif": "Артрозит – бўғимлар саломатлиги ва ҳаракатчанлигини қўллаб-қувватловчи биологик фаол қўшимча.\n\nТаркиби (1 таблеткада):\n• Глюкозамин сульфати – 500 мг\n• Хондроитин сульфати – 400 мг\n• Витамин C – 60 мг\n\nФойдаси:\n• Бўғим тўқималарини қайта тиклашга ёрдам беради\n• Илдиз ва оғриқни камайтиради\n• Синовиал суюқлик синтезини қўллаб-қувватлайди\n\nҚўллаш тартиби: 1 таблеткадан кунига 2 марта, овқат пайтида.\n\nҚўллашга қарши кўрсатма: глюкозамин ёки хондроитинга аллергия, ҳомиладорлик, лактация.\n\nҚандсиз. ГМОсиз.",  
        "hajm": "В ориг.(уп.) 50шт",  
        "rasm_path": "img//artrozid.jpg"  
    }
}  
